{
    "@class": "com.kony.gen.viz.model.component.KVizUserWidget",
    "DNDConfig": null,
    "_children_": [],
    "_height_": {
        "type": "string",
        "value": "64dp"
    },
    "_left_": {
        "type": "string",
        "value": "0dp"
    },
    "_margin_": [
        0,
        0,
        0,
        0
    ],
    "_orientation_": 1,
    "_padding_": [
        0,
        0,
        0,
        0
    ],
    "_percent_": true,
    "_skin_": "sf51dc37fd0a40178320b8330b005a98",
    "_top_": {
        "type": "string",
        "value": "0dp"
    },
    "_width_": {
        "type": "string",
        "value": "100%"
    },
    "areflexpropsreferenced": false,
    "autogrowmode": 0,
    "canUpdateUI": true,
    "clipbounds": false,
    "containerweight": 0,
    "dataDiffs": {
        "FormHeader": {
            "__events__": {},
            "__info__": {
                "isRoot": true,
                "kuid": "g235e16f4deb43068f768363f7963a53",
                "srcKUID": "ja2cbe8fda184c1caaab89eeae9fb281",
                "wType": "FlexContainer"
            },
            "autogrowMode": {
                "Default": 0
            },
            "height": {
                "Default": {
                    "type": "string",
                    "value": "64dp"
                }
            },
            "responsiveData": {}
        },
        "lblHdr": {
            "__events__": {},
            "__info__": {
                "kuid": "a285fcfc659645aa98058cd3817420b0",
                "srcKUID": "ecaffe136a7647ee89b97eff000d8e8c",
                "wType": "Label"
            },
            "responsiveData": {},
            "text": "History Details"
        }
    },
    "enablescrolling": true,
    "focusskin": "sf51dc37fd0a40178320b8330b005a98",
    "id": "FormHeader",
    "info": null,
    "iscustomlayout": false,
    "isdatareferenced": false,
    "isvisible": true,
    "kuid": "g235e16f4deb43068f768363f7963a53",
    "layouttype": 2,
    "masterType": 0,
    "name": "kony.ui.UserWidgetInstance",
    "parent": "flxRight",
    "pf": "frmSusHistoryDetails",
    "retaincontentalignment": false,
    "retainflexpositionproperties": false,
    "retainflowhorizontalalignment": false,
    "snapgridsize": 10,
    "snaptogrid": true,
    "sourceUserWidget": "ja2cbe8fda184c1caaab89eeae9fb281",
    "wType": "UserWidgetInstance",
    "zindex": 1
}