{
    "@class": "com.kony.gen.viz.model.component.KVizUserWidget",
    "DNDConfig": null,
    "_children_": [],
    "_height_": {
        "type": "string",
        "value": "64dp"
    },
    "_left_": {
        "type": "string",
        "value": "0dp"
    },
    "_margin_": [
        0,
        0,
        0,
        0
    ],
    "_orientation_": 1,
    "_padding_": [
        0,
        0,
        0,
        0
    ],
    "_percent_": true,
    "_skin_": "sf51dc37fd0a40178320b8330b005a98",
    "_top_": {
        "type": "string",
        "value": "0dp"
    },
    "_width_": {
        "type": "string",
        "value": "100%"
    },
    "android": {},
    "androidwearos": {},
    "areflexpropsreferenced": false,
    "autogrowmode": 0,
    "canUpdateUI": true,
    "clipbounds": false,
    "containerweight": 0,
    "dataDiffs": {
        "FormHeader": {
            "__events__": {},
            "__info__": {
                "isRoot": true,
                "kuid": "ef2877a3e8b544eeb160496f9d9158e4",
                "srcKUID": "ja2cbe8fda184c1caaab89eeae9fb281",
                "wType": "FlexContainer"
            },
            "autogrowMode": {
                "Default": 0
            },
            "centerY": {
                "Default": {
                    "type": "string",
                    "value": ""
                }
            },
            "height": {
                "Default": {
                    "type": "string",
                    "value": "64dp"
                }
            },
            "responsiveData": {},
            "top": {
                "Default": {
                    "type": "string",
                    "value": "0dp"
                }
            }
        },
        "lblHdr": {
            "__events__": {},
            "__info__": {
                "kuid": "cb0eb1e10507435aa52a27fdc182f777",
                "srcKUID": "ecaffe136a7647ee89b97eff000d8e8c",
                "wType": "Label"
            },
            "responsiveData": {},
            "text": "Remove Suspend List"
        }
    },
    "desktopweb": {},
    "enablescrolling": true,
    "focusskin": "sf51dc37fd0a40178320b8330b005a98",
    "id": "FormHeader",
    "info": null,
    "ipad": {},
    "iphone": {},
    "iscustomlayout": false,
    "isdatareferenced": false,
    "isvisible": true,
    "kiosk": {},
    "kuid": "ef2877a3e8b544eeb160496f9d9158e4",
    "layouttype": 2,
    "masterType": 0,
    "name": "kony.ui.UserWidgetInstance",
    "parent": "flxRight",
    "pf": "frmRemoveSuspend",
    "responsiveData": {},
    "retaincontentalignment": false,
    "retainflexpositionproperties": false,
    "retainflowhorizontalalignment": false,
    "snapgridsize": 10,
    "snaptogrid": true,
    "sourceUserWidget": "ja2cbe8fda184c1caaab89eeae9fb281",
    "spa": {},
    "spaan": {},
    "spaandroidtablet": {},
    "spabb": {},
    "spaip": {},
    "spaipad": {},
    "spamobile": {},
    "spatablet": {},
    "spawindowstablet": {},
    "spawinphone8": {},
    "tabrcandroid": {},
    "vizProps": {
        "hidewidgethierarchy": false
    },
    "wType": "UserWidgetInstance",
    "windows10": {},
    "windows8": {},
    "winphone10": {},
    "winphone8": {},
    "zindex": 1
}